Metadata-Version: 2.1
Name: pwea
Version: 0.3
Summary: A simple weather tool.
Home-page: https://gitlab.com/jeffreybarfield/myweather
Author: Jeff Barfield
Author-email: jeffreybarfield@protonmail.com
License: MIT
Platform: UNKNOWN
Classifier: Programming Language :: Python :: 3
Classifier: License :: OSI Approved :: MIT License
Classifier: Operating System :: OS Independent
Requires-Python: >=3.6
License-File: LICENSE
